LICENSE
MANIFEST.in
README.rst
setup.py
django_ipyfield.egg-info/PKG-INFO
django_ipyfield.egg-info/SOURCES.txt
django_ipyfield.egg-info/dependency_links.txt
django_ipyfield.egg-info/requires.txt
django_ipyfield.egg-info/top_level.txt
ipyfield/__init__.py
ipyfield/models.py
ipyfield/tests.py