Metadata-Version: 1.0
Name: django-ipyfield
Version: 0.1.6
Summary: IPy.IP instances with BigInt storage for django models
Home-page: https://bitbucket.org/onelson/django-ipyfield/
Author: Owen Nelson
Author-email: onelson@gmail.com
License: MIT
Keywords: ip,models,django
Platform: UNKNOWN
Classifier: Development Status :: 2 - Pre-Alpha
Classifier: Environment :: Web Environment
Classifier: Framework :: Django
Classifier: Intended Audience :: Developers
Classifier: License :: OSI Approved :: MIT License
Classifier: Operating System :: OS Independent
Classifier: Programming Language :: Python
Classifier: Topic :: Internet :: WWW/HTTP
Classifier: Topic :: Internet :: WWW/HTTP :: Dynamic Content
Classifier: Topic :: Internet :: WWW/HTTP :: WSGI
Classifier: Topic :: Software Development :: Libraries :: Application Frameworks
Classifier: Topic :: Software Development :: Libraries :: Python Modules
